rasa_chinese_service/__init__.py
rasa_chinese_service/core/__init__.py
rasa_chinese_service/core/policies/__init__.py
rasa_chinese_service/core/policies/stacked_bilstm_paddle_policy.py
rasa_chinese_service/core/policies/stacked_bilstm_tf_policy.py
rasa_chinese_service/nlu/__init__.py
rasa_chinese_service/nlu/classifiers/__init__.py
rasa_chinese_service/nlu/debugger/__init__.py
rasa_chinese_service/nlu/extractors/__init__.py
rasa_chinese_service/nlu/featurizers/__init__.py
rasa_chinese_service/nlu/tokenizers/__init__.py
rasa_chinese_service/nlu/tokenizers/lm_tokenizer.py
rasa_chinese_service/nlu/utils/__init__.py
rasa_chinese_service/utils/__init__.py
tests/__init__.py
tests/nlu/__init__.py
tests/nlu/tokenizers/__init__.py
tests/nlu/tokenizers/test_lm_tokenizer.py
rasa_chinese_service-2.2.1.dist-info/LICENSE
rasa_chinese_service-2.2.1.dist-info/METADATA
rasa_chinese_service-2.2.1.dist-info/WHEEL
rasa_chinese_service-2.2.1.dist-info/top_level.txt
rasa_chinese_service-2.2.1.dist-info/RECORD
